{
   "CodeGenerationMode": 2,
   "ContextClassName": "CubeProjetIndiContext",
   "ContextNamespace": null,
   "DefaultDacpacSchema": null,
   "FilterSchemas": false,
   "IncludeConnectionString": false,
   "ModelNamespace": null,
   "OutputContextPath": "Datas",
   "OutputPath": "Models",
   "PreserveCasingWithRegex": true,
   "ProjectRootNamespace": "Cube",
   "Schemas": null,
   "SelectedHandlebarsLanguage": 0,
   "SelectedToBeGenerated": 0,
   "Tables": [
      {
         "Name": "[dbo].[Cities]",
         "ObjectType": 0
      },
      {
         "Name": "[dbo].[Employs]",
         "ObjectType": 0
      },
      {
         "Name": "[dbo].[Services]",
         "ObjectType": 0
      }
   ],
   "UiHint": "vmahieux.CubeProjetIndi",
   "UncountableWords": null,
   "UseBoolPropertiesWithoutDefaultSql": false,
   "UseDatabaseNames": false,
   "UseDbContextSplitting": false,
   "UseFluentApiOnly": true,
   "UseHandleBars": false,
   "UseHierarchyId": false,
   "UseInflector": false,
   "UseLegacyPluralizer": false,
   "UseManyToManyEntity": false,
   "UseNoDefaultConstructor": false,
   "UseNoObjectFilter": false,
   "UseNodaTime": false,
   "UseNullableReferences": false,
   "UseSchemaFolders": false,
   "UseSpatial": false,
   "UseT4": false
}